xtssort/__init__.py
xtssort-0.0.7.dist-info/LICENSE
xtssort-0.0.7.dist-info/METADATA
xtssort-0.0.7.dist-info/WHEEL
xtssort-0.0.7.dist-info/top_level.txt
xtssort-0.0.7.dist-info/RECORD
